kgheartbeat/AGAPI.py
kgheartbeat/DataHubAPI.py
kgheartbeat/ExternalLink.py
kgheartbeat/Graph.py
kgheartbeat/GraphOfKG.gpickle
kgheartbeat/LODCloudAPI.py
kgheartbeat/LOVAPI.py
kgheartbeat/VoIDAnalyses.py
kgheartbeat/__init__.py
kgheartbeat/aggregator.py
kgheartbeat/bloomfilter.py
kgheartbeat/knowledge_graph.py
kgheartbeat/lov1.txt
kgheartbeat/lov2.txt
kgheartbeat/query.py
kgheartbeat/resources.py
kgheartbeat/sources.py
kgheartbeat/utils.py
kgheartbeat-0.2.6.dist-info/METADATA
kgheartbeat-0.2.6.dist-info/WHEEL
kgheartbeat-0.2.6.dist-info/top_level.txt
kgheartbeat-0.2.6.dist-info/RECORD
