Metadata-Version: 2.1
Name: kgheartbeat
Version: 0.2.6
Summary: Library that allows to perform Knowledge Graph (Linked Open Data) quality analysis.
Home-page: https://gabrielet0.github.io/KGHeartbeat-API/reference/
Author: Gabriele Tuozzo, Maria Angela Pellegrino
Author-email: gabrieletuozzo@gmail.com
License: MIT
Classifier: Intended Audience :: Developers
Classifier: License :: OSI Approved :: MIT License
Classifier: Programming Language :: Python
Classifier: Programming Language :: Python :: 3
Classifier: Programming Language :: Python :: 3.6
Classifier: Programming Language :: Python :: 3.7
Classifier: Programming Language :: Python :: 3.8
Classifier: Programming Language :: Python :: 3.9
Classifier: Operating System :: OS Independent
Requires-Dist: SPARQLWrapper >=2.0.0
Requires-Dist: networkx >=2.6.3
Requires-Dist: validators >=0.18.2
Requires-Dist: requests >=2.27.1
Requires-Dist: rdflib >=6.1.1
Requires-Dist: numpy >=1.19.5
Requires-Dist: mmh3 >=3.0.0
Requires-Dist: mechanize >=0.4.7
Requires-Dist: bitarray >=2.4.0
Requires-Dist: scipy >=1.7.3
